cetus_cearcher/__init__.py
cetus_cearcher/__main__.py
cetus_cearcher/examples/certstream.json
cetus_cearcher/examples/dns.json
cetus_cearcher/main.py
cetus_cearcher/search.py
cetus_cearcher/third_party/singlesource/__init__.py
cetus_cearcher/third_party/singlesource/errors.py
cetus_cearcher/third_party/singlesource/version.py
cetus_cearcher-0.1.1.dist-info/entry_points.txt
cetus_cearcher-0.1.1.dist-info/WHEEL
cetus_cearcher-0.1.1.dist-info/METADATA
cetus_cearcher-0.1.1.dist-info/RECORD
