Metadata-Version: 2.1
Name: cetus-cearcher
Version: 0.1.1
Summary: Client for the Cetus API
Home-page: https://github.com/korrosivesec/cetus-cearcher
Author: Kory Kyzar
Author-email: k2@korrosivesecurity.com
Requires-Python: >=3.7,<4.0
Classifier: Programming Language :: Python :: 3
Classifier: Programming Language :: Python :: 3.7
Classifier: Programming Language :: Python :: 3.8
Classifier: Programming Language :: Python :: 3.9
Requires-Dist: requests (>=2.25.1,<3.0.0)
Requires-Dist: rich (>=10.3.0,<11.0.0)
Requires-Dist: typer (>=0.3.2,<0.4.0)
Requires-Dist: typer-cli (>=0.0.11,<0.0.12)
Project-URL: Repository, https://github.com/korrosivesec/cetus-cearcher
